immoney/__init__.py
immoney/_base.py
immoney/_cache.py
immoney/_frozen.py
immoney/_parsers.py
immoney/_pydantic.py
immoney/_version.py
immoney/babel.py
immoney/currencies.py
immoney/errors.py
immoney/py.typed
immoney/registry.py
immoney-0.11.0.dist-info/LICENSE
immoney-0.11.0.dist-info/METADATA
immoney-0.11.0.dist-info/WHEEL
immoney-0.11.0.dist-info/top_level.txt
immoney-0.11.0.dist-info/RECORD
