Metadata-Version: 2.1
Name: immoney
Version: 0.11.0
Summary: Immutable money types for Python
Author-email: Anton Agestam <git@antonagestam.se>
License: BSD-3-Clause
Project-URL: Source Repository, https://github.com/antonagestam/immoney/
Project-URL: Bug Tracker, https://github.com/antonagestam/immoney/issues
Keywords: money,finance,fintech,type-driven,immutable
Classifier: Intended Audience :: Developers
Classifier: Operating System :: OS Independent
Classifier: Programming Language :: Python
Classifier: Programming Language :: Python :: 3
Classifier: Programming Language :: Python :: 3 :: Only
Classifier: Programming Language :: Python :: 3.10
Classifier: Programming Language :: Python :: 3.11
Classifier: Programming Language :: Python :: 3.12
Classifier: Programming Language :: Python :: 3.13
Classifier: Development Status :: 4 - Beta
Classifier: Typing :: Typed
Requires-Python: >=3.10
License-File: LICENSE
Requires-Dist: typing-extensions >=4.6.3
Requires-Dist: abcattrs >=0.3.2
Provides-Extra: babel
Requires-Dist: babel >=2.12.1 ; extra == 'babel'
Provides-Extra: pydantic
Requires-Dist: pydantic >=2.0.3 ; extra == 'pydantic'
Requires-Dist: pydantic-core >=2.10 ; extra == 'pydantic'
Provides-Extra: test
Requires-Dist: pytest ; extra == 'test'
Requires-Dist: coverage ; extra == 'test'
Requires-Dist: hypothesis ; extra == 'test'
Provides-Extra: type-check
Requires-Dist: mypy ; extra == 'type-check'
Requires-Dist: types-setuptools ; extra == 'type-check'
Requires-Dist: types-babel ; extra == 'type-check'
